build/lib/docs/conf.py
build/lib/openpyweb/App.py
build/lib/openpyweb/Config.py
build/lib/openpyweb/Controllers.py
build/lib/openpyweb/Flash.py
build/lib/openpyweb/Hash.py
build/lib/openpyweb/Lang.py
build/lib/openpyweb/Log.py
build/lib/openpyweb/Model.py
build/lib/openpyweb/Request.py
build/lib/openpyweb/Router.py
build/lib/openpyweb/Session.py
build/lib/openpyweb/Version.py
build/lib/openpyweb/Web.py
build/lib/openpyweb/__init__.py
build/lib/openpyweb/__main__.py
build/lib/openpyweb/serv.py
build/lib/openpyweb/Core/File.py
build/lib/openpyweb/Core/Functions.py
build/lib/openpyweb/Core/Helpers.py
build/lib/openpyweb/Core/SMTP.py
build/lib/openpyweb/Core/__init__.py
build/lib/openpyweb/Core/env.py
build/lib/openpyweb/Core/requirement.py
build/lib/openpyweb/Driver/Schema.py
build/lib/openpyweb/Driver/__init__.py
build/lib/openpyweb/Driver/DB/Table.py
build/lib/openpyweb/Driver/DB/__init__.py
build/lib/openpyweb/Driver/DB/MYSQL/MYSQL.py
build/lib/openpyweb/Driver/DB/MYSQL/__init__.py
build/lib/openpyweb/Driver/DB/Oracle/Oracle.py
build/lib/openpyweb/Driver/DB/Oracle/__init__.py
build/lib/openpyweb/Driver/DB/SQLite/SQLite.py
build/lib/openpyweb/Driver/DB/SQLite/__init__.py
build/lib/openpyweb/Driver/DB/pyPgSQL/__init__.py
build/lib/openpyweb/Driver/DB/pyPgSQL/pyPgSQL.py
build/lib/openpyweb/Editor/Compiler.py
build/lib/openpyweb/Editor/Node.py
build/lib/openpyweb/Editor/Resolver.py
build/lib/openpyweb/Editor/Template.py
build/lib/openpyweb/Editor/_Fragment.py
build/lib/openpyweb/Editor/__init__.py
build/lib/openpyweb/Functions/__.py
build/lib/openpyweb/Functions/__init__.py
build/lib/openpyweb/Functions/agent.py
build/lib/openpyweb/Functions/count.py
build/lib/openpyweb/Functions/curl.py
build/lib/openpyweb/Functions/extend.py
build/lib/openpyweb/Functions/include.py
build/lib/openpyweb/Functions/ip.py
build/lib/openpyweb/Functions/iteration.py
build/lib/openpyweb/Functions/now.py
build/lib/openpyweb/Functions/pagination.py
build/lib/openpyweb/Functions/path.py
openpyweb-2.1.1.dist-info/LICENSE.txt
openpyweb-2.1.1.dist-info/METADATA
openpyweb-2.1.1.dist-info/WHEEL
openpyweb-2.1.1.dist-info/entry_points.txt
openpyweb-2.1.1.dist-info/top_level.txt
openpyweb-2.1.1.dist-info/RECORD
