Metadata-Version: 2.1
Name: openpyweb
Version: 2.1.1
Summary: openpyweb is a python framework built to enhance web development fast and easy, also help web developers to build more apps with less codes
Home-page: https://github.com/emmanuelessiens/openpyweb
Author: Emmanuel Essien
Author-email: emmanuelessiens@outlook.com
Maintainer: Emmanuel Essien
Maintainer-email: emmanuelessiens@outlook.com
License: GPL3
Keywords: mvc,oop,module,python,framework,web,app,openpyweb,web,web development
Classifier: Environment :: Console
Classifier: Environment :: Web Environment
Classifier: Intended Audience :: Developers
Classifier: License :: OSI Approved :: BSD License
Classifier: Topic :: Office/Business
Classifier: Topic :: Internet :: WWW/HTTP :: Dynamic Content
Classifier: Topic :: Internet :: WWW/HTTP :: WSGI :: Application
Classifier: Topic :: Software Development :: Libraries :: Application Frameworks
Classifier: Topic :: Software Development :: Libraries :: Python Modules
Classifier: Programming Language :: Python :: 3
Classifier: Programming Language :: Python :: 3.4
Classifier: Programming Language :: Python :: 3.5
Classifier: Programming Language :: Python :: 3.6
Classifier: Programming Language :: Python :: 3.7
Classifier: Programming Language :: Python :: 3.8
Classifier: Programming Language :: Python :: 3.9
Classifier: Programming Language :: Python :: 3.10
Classifier: Programming Language :: Python :: 3.11
Classifier: Programming Language :: Python :: 3.12
Classifier: Programming Language :: Python
Requires-Python: >3, >=3.3
License-File: LICENSE.txt
Requires-Dist: Pillow
Requires-Dist: colorama
Requires-Dist: cx-Oracle
Requires-Dist: mysql-connector-python
Requires-Dist: psycopg2-binary
